ngsgui/__init__.py
ngsgui/__main__.py
ngsgui/console.py
ngsgui/gl.py
ngsgui/gl_interface.py
ngsgui/glmath.py
ngsgui/globalSettings.py
ngsgui/glwindow.py
ngsgui/gui.py
ngsgui/jupyter.py
ngsgui/menu.py
ngsgui/plot.py
ngsgui/scenes.py
ngsgui/settings.py
ngsgui/stdPipes.py
ngsgui/systemmonitor.py
ngsgui/thread.py
ngsgui/toolbox.py
ngsgui/widgets.py
ngsgui/icons/__init__.py
ngsgui/icons/color.png
ngsgui/icons/down-arrow.png
ngsgui/icons/globalColor.png
ngsgui/icons/globalLight.png
ngsgui/icons/globalScissors.png
ngsgui/icons/hidden.png
ngsgui/icons/kill.png
ngsgui/icons/light.png
ngsgui/icons/next.png
ngsgui/icons/nocolor.png
ngsgui/icons/nolight.png
ngsgui/icons/noscissors.png
ngsgui/icons/run.png
ngsgui/icons/save.png
ngsgui/icons/scissors.png
ngsgui/icons/search.png
ngsgui/icons/visible.png
ngsgui/shader/__init__.py
ngsgui/shader/clipping.geom
ngsgui/shader/colorbar.frag
ngsgui/shader/colorbar.vert
ngsgui/shader/cross.frag
ngsgui/shader/cross.vert
ngsgui/shader/fieldlines.frag
ngsgui/shader/fieldlines.vert
ngsgui/shader/fieldlines_draw.geom
ngsgui/shader/fieldlines_filter.geom
ngsgui/shader/filter_elements.geom
ngsgui/shader/font.frag
ngsgui/shader/font.geom
ngsgui/shader/font.vert
ngsgui/shader/generate_interpolation_shader.py
ngsgui/shader/generated_interpolation.inc
ngsgui/shader/geo.frag
ngsgui/shader/geo.vert
ngsgui/shader/geom2d.vert
ngsgui/shader/interpolation.inc
ngsgui/shader/isosurface.geom
ngsgui/shader/mesh.frag
ngsgui/shader/mesh.tese
ngsgui/shader/mesh.vert
ngsgui/shader/numbers.geom
ngsgui/shader/pass_through.vert
ngsgui/shader/poly.py
ngsgui/shader/solution.frag
ngsgui/shader/utils.inc
ngsgui/shader/vectors.frag
ngsgui/shader/vectors.vert
ngsgui/shader/vectors_draw.geom
ngsgui/shader/vectors_filter.geom
ngsgui/spyder_ngsgui/__init__.py
ngsgui/spyder_ngsgui/ngsgui_plugin.py
ngsgui/spyder_ngsgui/startup.py
spyder_ngsgui/__init__.py
spyder_ngsgui/ngsgui_plugin.py
spyder_ngsgui/startup.py
ngsgui-0.1.10.dist-info/METADATA
ngsgui-0.1.10.dist-info/WHEEL
ngsgui-0.1.10.dist-info/entry_points.txt
ngsgui-0.1.10.dist-info/top_level.txt
ngsgui-0.1.10.dist-info/RECORD
