Metadata-Version: 2.1
Name: ngsgui
Version: 0.1.10
Summary: New graphical interface for NGSolve
Home-page: UNKNOWN
License: UNKNOWN
Platform: UNKNOWN
Classifier: Programming Language :: Python :: 3
Classifier: Operating System :: OS Independent
Classifier: Development Status :: 2 - Pre-Alpha
Classifier: Environment :: X11 Applications :: Qt
Classifier: License :: OSI Approved :: GNU Lesser General Public License v3 or later (LGPLv3+)
Requires-Dist: PyOpenGL
Requires-Dist: psutil
Requires-Dist: qtconsole (>=4.4.0)
Requires-Dist: numpy
Requires-Dist: matplotlib (>=2.2.3)
Requires-Dist: qtpy (>=1.5.2)
Requires-Dist: ipykernel (<5)
Provides-Extra: test
Requires-Dist: pytest-qt ; extra == 'test'
